AlphabetPy/__init__.py
AlphabetPy/alphabet.py
AlphabetPy/planar.py
AlphabetPy/stereo.py
AlphabetPy-1.0.dist-info/DESCRIPTION.rst
AlphabetPy-1.0.dist-info/METADATA
AlphabetPy-1.0.dist-info/RECORD
AlphabetPy-1.0.dist-info/WHEEL
AlphabetPy-1.0.dist-info/entry_points.txt
AlphabetPy-1.0.dist-info/metadata.json
AlphabetPy-1.0.dist-info/top_level.txt
