Metadata-Version: 2.0
Name: AlphabetPy
Version: 1.0
Summary: A python tool to output characters in console/shell
Home-page: https://github.com/RayZhao1998/alphabetPy
Author: Ray Zhao
Author-email: rayzhao98@163.com
License: MIT
Platform: UNKNOWN
